serializers/__init__.py
serializers/factory_serializer.py
serializers/dict_serializer/__init__.py
serializers/dict_serializer/functions.py
serializers/json/__init__.py
serializers/json/json.py
serializers/json/parse_json.py
serializers/xml/__init__.py
serializers/xml/xml.py
serializers/xml/xml_parser.py
serializer_for_igi-1.9.dist-info/METADATA
serializer_for_igi-1.9.dist-info/WHEEL
serializer_for_igi-1.9.dist-info/top_level.txt
serializer_for_igi-1.9.dist-info/RECORD
