Metadata-Version: 2.1
Name: serializer-for-igi
Version: 1.9
Summary: library for python serialization as lab
Home-page: https://github.com/SeMsei/pythn_igi/tree/lab3/Lab_3
Author: Denis Fomichevskiy
Author-email: fomichevsjiy@gmail.com
License: UNKNOWN
Platform: UNKNOWN
Classifier: Intended Audience :: Developers
Classifier: Programming Language :: Python :: 3.10
Classifier: Operating System :: OS Independent
